xaler/__init__.py
xaler/main.py
xaler-0.1.1.data/scripts/xaler
xaler-0.1.1.dist-info/METADATA
xaler-0.1.1.dist-info/RECORD
xaler-0.1.1.dist-info/WHEEL
xaler-0.1.1.dist-info/entry_points.txt
xaler-0.1.1.dist-info/top_level.txt
